acinonyx/__init__.py
acinonyx/__version__.py
acinonyx/acinonyx.py
acinonyx/utils.py
acinonyx-0.1.0.dist-info/METADATA
acinonyx-0.1.0.dist-info/WHEEL
acinonyx-0.1.0.dist-info/top_level.txt
acinonyx-0.1.0.dist-info/RECORD
